gourd/__init__.py
gourd/gourd.py
gourd/gourd_message.py
gourd/mqtt_log_handler.py
gourd/mqtt_wildcard.py
gourd/script.py
tests/__init__.py
tests/test_mqtt_wildcard.py
gourd-0.1.3.dist-info/LICENSE
gourd-0.1.3.dist-info/METADATA
gourd-0.1.3.dist-info/WHEEL
gourd-0.1.3.dist-info/entry_points.txt
gourd-0.1.3.dist-info/top_level.txt
gourd-0.1.3.dist-info/RECORD
