Metadata-Version: 2.1
Name: gourd
Version: 0.1.3
Summary: An opinionated framework for writing MQTT applications.
Author: skullydazed
Author-email: skullydazed@gmail.com
License: MIT License
Project-URL: Bug Tracker, https://github.com/clueboard/gourd/issues
Project-URL: Homepage, https://gourd.clueboard.co/
Project-URL: Source, https://github.com/clueboard/gourd/
Classifier: Development Status :: 3 - Alpha
Classifier: Environment :: Console
Classifier: Intended Audience :: Developers
Classifier: Intended Audience :: System Administrators
Classifier: License :: OSI Approved :: MIT License
Classifier: Natural Language :: English
Classifier: Programming Language :: Python :: 3 :: Only
Classifier: Topic :: Scientific/Engineering
Classifier: Topic :: Software Development
Classifier: Topic :: Software Development :: Libraries :: Python Modules
Classifier: Topic :: Utilities
Requires-Python: >=3.7
License-File: LICENSE
Requires-Dist: milc
Requires-Dist: paho-mqtt
